{"files":{"packages/core/dist":{"size":0,"mtime_nanos":0,"mode":0,"is_dir":true},"packages/core/dist/index.cjs":{"size":8468,"mtime_nanos":1783013104590359311,"mode":420,"is_dir":false},"packages/core/dist/index.js":{"size":8195,"mtime_nanos":1783013104590362353,"mode":420,"is_dir":false},"packages/core/dist/index.js.map":{"size":21303,"mtime_nanos":1783013104590870057,"mode":420,"is_dir":false},"packages/core/.turbo/turbo-build.log":{"size":809,"mtime_nanos":1783013105265966791,"mode":420,"is_dir":false},"packages/core/dist/index.cjs.map":{"size":21306,"mtime_nanos":1783013104590875723,"mode":420,"is_dir":false},"packages/core/dist/index.d.cts":{"size":4764,"mtime_nanos":1783013105245547707,"mode":420,"is_dir":false},"packages/core/dist/index.d.ts":{"size":4764,"mtime_nanos":1783013105245549291,"mode":420,"is_dir":false}},"order":["packages/core/.turbo/turbo-build.log","packages/core/dist","packages/core/dist/index.cjs","packages/core/dist/index.cjs.map","packages/core/dist/index.d.cts","packages/core/dist/index.d.ts","packages/core/dist/index.js","packages/core/dist/index.js.map"]}